sendbase_email/__init__.py
sendbase_email/client.py
sendbase_email/exceptions.py
sendbase_email/http_client.py
sendbase_email/models.py
sendbase_email/py.typed
sendbase_email/clients/__init__.py
sendbase_email/clients/billing.py
sendbase_email/clients/domains.py
sendbase_email/clients/emails.py
sendbase_email/clients/inbound.py
sendbase_email/clients/messages.py
sendbase_email/clients/templates.py
sendbase_email/clients/tenants.py
sendbase_email/clients/webhooks.py
sendbase_email-1.0.5.dist-info/licenses/LICENSE
sendbase_email-1.0.5.dist-info/METADATA
sendbase_email-1.0.5.dist-info/WHEEL
sendbase_email-1.0.5.dist-info/top_level.txt
sendbase_email-1.0.5.dist-info/RECORD
