Metadata-Version: 2.4
Name: sendbase-email
Version: 1.0.5
Summary: Official Python SDK for the SendBase Email API. Send transactional emails, manage domains, templates, and more.
Author-email: SendBase <support@sendbase.app>
License-Expression: MIT
Project-URL: Homepage, https://sendbase.app
Project-URL: Documentation, https://docs.sendbase.app
Project-URL: Repository, https://github.com/sendbase/sendbase-python
Project-URL: Issues, https://github.com/sendbase/sendbase-python/issues
Keywords: email,api,sdk,sendbase,transactional-email
Classifier: Development Status :: 5 - Production/Stable
Classifier: Intended Audience :: Developers
Classifier: Operating System :: OS Independent
Classifier: Programming Language :: Python :: 3
Classifier: Programming Language :: Python :: 3.9
Classifier: Programming Language :: Python :: 3.10
Classifier: Programming Language :: Python :: 3.11
Classifier: Programming Language :: Python :: 3.12
Classifier: Topic :: Communications :: Email
Classifier: Topic :: Software Development :: Libraries :: Python Modules
Classifier: Typing :: Typed
Requires-Python: >=3.9
License-File: LICENSE
Requires-Dist: httpx>=0.25.0
Requires-Dist: pydantic>=2.0.0
Provides-Extra: dev
Requires-Dist: pytest>=7.0.0; extra == "dev"
Requires-Dist: pytest-asyncio>=0.21.0; extra == "dev"
Requires-Dist: respx>=0.20.0; extra == "dev"
Dynamic: license-file
